kerberosauthenticator/__init__.py
kerberosauthenticator/_version.py
kerberosauthenticator/auth.py
kerberosauthenticator/templates/kerberos_login_error.html
kerberosauthenticator/tests/conftest.py
kerberosauthenticator/tests/test_authenticator.py
jupyterhub_kerberosauthenticator-0.2.0.dist-info/LICENSE
jupyterhub_kerberosauthenticator-0.2.0.dist-info/METADATA
jupyterhub_kerberosauthenticator-0.2.0.dist-info/WHEEL
jupyterhub_kerberosauthenticator-0.2.0.dist-info/top_level.txt
jupyterhub_kerberosauthenticator-0.2.0.dist-info/RECORD
